{
  "$schema": "https://developer.microsoft.com/json-schemas/fabric/item/report/definition/visualContainer/2.9.0/schema.json",
  "name": "5a483ea6421996b6fb05",
  "position": {
    "x": 1138,
    "y": 690,
    "z": 0,
    "height": 340,
    "width": 728,
    "tabOrder": 0
  },
  "visual": {
    "visualType": "tableEx",
    "query": {
      "queryState": {
        "Values": {
          "projections": [
            {
              "field": {
                "Column": {
                  "Expression": {
                    "SourceRef": {
                      "Entity": "d_produto"
                    }
                  },
                  "Property": "NomeProduto"
                }
              },
              "queryRef": "d_produto.NomeProduto",
              "nativeQueryRef": "Produto",
              "displayName": "Produto"
            },
            {
              "field": {
                "Aggregation": {
                  "Expression": {
                    "Column": {
                      "Expression": {
                        "SourceRef": {
                          "Entity": "f_vendas"
                        }
                      },
                      "Property": "Unidades"
                    }
                  },
                  "Function": 0
                }
              },
              "queryRef": "Sum(f_vendas.Unidades)",
              "nativeQueryRef": "Unidades",
              "displayName": "Unidades"
            },
            {
              "field": {
                "Measure": {
                  "Expression": {
                    "SourceRef": {
                      "Entity": "Medidas"
                    }
                  },
                  "Property": "ReceitaBruta"
                }
              },
              "queryRef": "d_produto.ReceitaBruta",
              "nativeQueryRef": "Receita Bruta",
              "displayName": "Receita Bruta"
            },
            {
              "field": {
                "Measure": {
                  "Expression": {
                    "SourceRef": {
                      "Entity": "Medidas"
                    }
                  },
                  "Property": "CustoTotal"
                }
              },
              "queryRef": "d_produto.CustoTotal",
              "nativeQueryRef": "Custo",
              "displayName": "Custo"
            },
            {
              "field": {
                "Measure": {
                  "Expression": {
                    "SourceRef": {
                      "Entity": "Medidas"
                    }
                  },
                  "Property": "TicketMedio"
                }
              },
              "queryRef": "d_produto.TicketMedio",
              "nativeQueryRef": "Ticket Médio",
              "displayName": "Ticket Médio"
            },
            {
              "field": {
                "Measure": {
                  "Expression": {
                    "SourceRef": {
                      "Entity": "Medidas"
                    }
                  },
                  "Property": "LucroBruto"
                }
              },
              "queryRef": "d_produto.LucroBruto",
              "nativeQueryRef": "Lucro Bruto",
              "displayName": "Lucro Bruto"
            }
          ]
        }
      },
      "sortDefinition": {
        "sort": [
          {
            "field": {
              "Measure": {
                "Expression": {
                  "SourceRef": {
                    "Entity": "Medidas"
                  }
                },
                "Property": "ReceitaBruta"
              }
            },
            "direction": "Descending"
          }
        ]
      }
    },
    "objects": {
      "columnHeaders": [
        {
          "properties": {
            "autoSizeColumnWidth": {
              "expr": {
                "Literal": {
                  "Value": "true"
                }
              }
            },
            "fontFamily": {
              "expr": {
                "Literal": {
                  "Value": "'''Segoe UI Semibold'', wf_segoe-ui_semibold, helvetica, arial, sans-serif'"
                }
              }
            },
            "fontSize": {
              "expr": {
                "Literal": {
                  "Value": "15D"
                }
              }
            },
            "fontColor": {
              "solid": {
                "color": {
                  "expr": {
                    "ThemeDataColor": {
                      "ColorId": 1,
                      "Percent": 0
                    }
                  }
                }
              }
            },
            "alignment": {
              "expr": {
                "Literal": {
                  "Value": "'Left'"
                }
              }
            },
            "columnAdjustment": {
              "expr": {
                "Literal": {
                  "Value": "'fitToContent'"
                }
              }
            }
          }
        }
      ],
      "columnWidth": [
        {
          "properties": {
            "value": {
              "expr": {
                "Literal": {
                  "Value": "101.72355065469318D"
                }
              }
            }
          },
          "selector": {
            "metadata": "Sum(f_vendas.Unidades)"
          }
        },
        {
          "properties": {
            "value": {
              "expr": {
                "Literal": {
                  "Value": "106.81235867890254D"
                }
              }
            }
          },
          "selector": {
            "metadata": "d_produto.NomeProduto"
          }
        },
        {
          "properties": {
            "value": {
              "expr": {
                "Literal": {
                  "Value": "163.5715685229277D"
                }
              }
            }
          },
          "selector": {
            "metadata": "d_produto.ReceitaBruta"
          }
        }
      ],
      "columnFormatting": [
        {
          "properties": {
            "alignment": {
              "expr": {
                "Literal": {
                  "Value": "'Right'"
                }
              }
            },
            "labelDisplayUnits": {
              "expr": {
                "Literal": {
                  "Value": "1000D"
                }
              }
            }
          },
          "selector": {
            "metadata": "Sum(f_vendas.Unidades)"
          }
        },
        {
          "properties": {
            "alignment": {
              "expr": {
                "Literal": {
                  "Value": "'Right'"
                }
              }
            },
            "labelDisplayUnits": {
              "expr": {
                "Literal": {
                  "Value": "1000000D"
                }
              }
            }
          },
          "selector": {
            "metadata": "d_produto.ReceitaBruta"
          }
        },
        {
          "properties": {
            "alignment": {
              "expr": {
                "Literal": {
                  "Value": "'Right'"
                }
              }
            },
            "labelDisplayUnits": {
              "expr": {
                "Literal": {
                  "Value": "1000000D"
                }
              }
            },
            "dataBars": {
              "positiveColor": {
                "solid": {
                  "color": {
                    "expr": {
                      "Literal": {
                        "Value": "'#DACCE5'"
                      }
                    }
                  }
                }
              },
              "negativeColor": {
                "solid": {
                  "color": {
                    "expr": {
                      "Literal": {
                        "Value": "'minColor'"
                      }
                    }
                  }
                }
              },
              "axisColor": {
                "solid": {
                  "color": {
                    "expr": {
                      "Literal": {
                        "Value": "'foreground'"
                      }
                    }
                  }
                }
              },
              "reverseDirection": {
                "expr": {
                  "Literal": {
                    "Value": "false"
                  }
                }
              },
              "hideText": {
                "expr": {
                  "Literal": {
                    "Value": "false"
                  }
                }
              },
              "totalMatchingOption": {
                "expr": {
                  "Literal": {
                    "Value": "1L"
                  }
                }
              }
            }
          },
          "selector": {
            "metadata": "d_produto.LucroBruto"
          }
        },
        {
          "properties": {
            "alignment": {
              "expr": {
                "Literal": {
                  "Value": "'Right'"
                }
              }
            }
          },
          "selector": {
            "metadata": "d_produto.TicketMedio"
          }
        },
        {
          "properties": {
            "alignment": {
              "expr": {
                "Literal": {
                  "Value": "'Right'"
                }
              }
            },
            "labelDisplayUnits": {
              "expr": {
                "Literal": {
                  "Value": "1000000D"
                }
              }
            }
          },
          "selector": {
            "metadata": "d_produto.CustoTotal"
          }
        }
      ],
      "grid": [
        {
          "properties": {
            "outlineColor": {
              "solid": {
                "color": {
                  "expr": {
                    "ThemeDataColor": {
                      "ColorId": 1,
                      "Percent": 0
                    }
                  }
                }
              }
            },
            "outlineWeight": {
              "expr": {
                "Literal": {
                  "Value": "3D"
                }
              }
            },
            "gridVertical": {
              "expr": {
                "Literal": {
                  "Value": "false"
                }
              }
            },
            "gridVerticalColor": {
              "solid": {
                "color": {
                  "expr": {
                    "ThemeDataColor": {
                      "ColorId": 1,
                      "Percent": 0
                    }
                  }
                }
              }
            },
            "gridVerticalWeight": {
              "expr": {
                "Literal": {
                  "Value": "2D"
                }
              }
            },
            "gridHorizontalColor": {
              "solid": {
                "color": {
                  "expr": {
                    "ThemeDataColor": {
                      "ColorId": 1,
                      "Percent": 0
                    }
                  }
                }
              }
            },
            "gridHorizontalWeight": {
              "expr": {
                "Literal": {
                  "Value": "1D"
                }
              }
            },
            "rowPadding": {
              "expr": {
                "Literal": {
                  "Value": "4D"
                }
              }
            },
            "imageHeight": {
              "expr": {
                "Literal": {
                  "Value": "75D"
                }
              }
            }
          }
        }
      ],
      "values": [
        {
          "properties": {
            "fontSize": {
              "expr": {
                "Literal": {
                  "Value": "14D"
                }
              }
            },
            "fontColorPrimary": {
              "solid": {
                "color": {
                  "expr": {
                    "ThemeDataColor": {
                      "ColorId": 1,
                      "Percent": 0
                    }
                  }
                }
              }
            }
          }
        }
      ]
    },
    "visualContainerObjects": {
      "background": [
        {
          "properties": {
            "show": {
              "expr": {
                "Literal": {
                  "Value": "false"
                }
              }
            },
            "transparency": {
              "expr": {
                "Literal": {
                  "Value": "0D"
                }
              }
            }
          }
        }
      ],
      "stylePreset": [
        {
          "properties": {
            "name": {
              "expr": {
                "Literal": {
                  "Value": "'None'"
                }
              }
            }
          }
        }
      ],
      "title": [
        {
          "properties": {
            "titleWrap": {
              "expr": {
                "Literal": {
                  "Value": "true"
                }
              }
            }
          }
        }
      ],
      "border": [
        {
          "properties": {
            "width": {
              "expr": {
                "Literal": {
                  "Value": "1D"
                }
              }
            }
          }
        }
      ]
    },
    "drillFilterOtherVisuals": true
  }
}