{
  "$schema": "https://developer.microsoft.com/json-schemas/fabric/item/report/definition/visualContainer/2.9.0/schema.json",
  "name": "bd65a01777a6f66fed06",
  "position": {
    "x": 25.843828715365241,
    "y": 13.602015113350125,
    "z": 0,
    "height": 1051.4357682619648,
    "width": 1878.4382871536525,
    "tabOrder": 0
  },
  "visual": {
    "visualType": "tableEx",
    "query": {
      "queryState": {
        "Values": {
          "projections": [
            {
              "field": {
                "Column": {
                  "Expression": {
                    "SourceRef": {
                      "Entity": "DocMedidasDAX"
                    }
                  },
                  "Property": "Table"
                }
              },
              "queryRef": "DocMedidasDAX.Table",
              "nativeQueryRef": "Table"
            },
            {
              "field": {
                "Column": {
                  "Expression": {
                    "SourceRef": {
                      "Entity": "DocMedidasDAX"
                    }
                  },
                  "Property": "Name"
                }
              },
              "queryRef": "DocMedidasDAX.Name",
              "nativeQueryRef": "Name"
            },
            {
              "field": {
                "Column": {
                  "Expression": {
                    "SourceRef": {
                      "Entity": "DocMedidasDAX"
                    }
                  },
                  "Property": "Expression"
                }
              },
              "queryRef": "DocMedidasDAX.Expression",
              "nativeQueryRef": "Expression"
            },
            {
              "field": {
                "Column": {
                  "Expression": {
                    "SourceRef": {
                      "Entity": "DocMedidasDAX"
                    }
                  },
                  "Property": "Description"
                }
              },
              "queryRef": "DocMedidasDAX.Description",
              "nativeQueryRef": "Description"
            }
          ]
        }
      },
      "sortDefinition": {
        "sort": [
          {
            "field": {
              "Column": {
                "Expression": {
                  "SourceRef": {
                    "Entity": "DocMedidasDAX"
                  }
                },
                "Property": "Description"
              }
            },
            "direction": "Descending"
          }
        ]
      }
    },
    "objects": {
      "columnWidth": [
        {
          "properties": {
            "value": {
              "expr": {
                "Literal": {
                  "Value": "133.5735574005597D"
                }
              }
            }
          },
          "selector": {
            "metadata": "Sum(f_vendas.Unidades)"
          }
        },
        {
          "properties": {
            "value": {
              "expr": {
                "Literal": {
                  "Value": "106.81235867890254D"
                }
              }
            }
          },
          "selector": {
            "metadata": "d_produto.NomeProduto"
          }
        },
        {
          "properties": {
            "value": {
              "expr": {
                "Literal": {
                  "Value": "200.0681019856539D"
                }
              }
            }
          },
          "selector": {
            "metadata": "d_produto.ReceitaBruta"
          }
        },
        {
          "properties": {
            "value": {
              "expr": {
                "Literal": {
                  "Value": "67.79433419021855D"
                }
              }
            }
          },
          "selector": {
            "metadata": "d_representanteVendas.IconeRanking"
          }
        },
        {
          "properties": {
            "value": {
              "expr": {
                "Literal": {
                  "Value": "206.3204097595612D"
                }
              }
            }
          },
          "selector": {
            "metadata": "d_representanteVendas.NomeRepresentante"
          }
        },
        {
          "properties": {
            "value": {
              "expr": {
                "Literal": {
                  "Value": "150D"
                }
              }
            }
          },
          "selector": {
            "metadata": "f_vendas.QuantidadeTotal"
          }
        },
        {
          "properties": {
            "value": {
              "expr": {
                "Literal": {
                  "Value": "606.8207072049651D"
                }
              }
            }
          },
          "selector": {
            "metadata": "DocMedidasDAX.Expression"
          }
        },
        {
          "properties": {
            "value": {
              "expr": {
                "Literal": {
                  "Value": "927.4450993326714D"
                }
              }
            }
          },
          "selector": {
            "metadata": "DocMedidasDAX.Description"
          }
        }
      ],
      "columnHeaders": [
        {
          "properties": {
            "fontFamily": {
              "expr": {
                "Literal": {
                  "Value": "'''Segoe UI Semibold'', wf_segoe-ui_semibold, helvetica, arial, sans-serif'"
                }
              }
            },
            "fontSize": {
              "expr": {
                "Literal": {
                  "Value": "18D"
                }
              }
            },
            "fontColor": {
              "solid": {
                "color": {
                  "expr": {
                    "ThemeDataColor": {
                      "ColorId": 0,
                      "Percent": 0
                    }
                  }
                }
              }
            },
            "alignment": {
              "expr": {
                "Literal": {
                  "Value": "'Left'"
                }
              }
            },
            "columnAdjustment": {
              "expr": {
                "Literal": {
                  "Value": "'fitToContent'"
                }
              }
            },
            "backColor": {
              "solid": {
                "color": {
                  "expr": {
                    "Literal": {
                      "Value": "'#4A1E6D'"
                    }
                  }
                }
              }
            }
          }
        }
      ],
      "values": [
        {
          "properties": {
            "fontSize": {
              "expr": {
                "Literal": {
                  "Value": "16D"
                }
              }
            },
            "fontColorPrimary": {
              "solid": {
                "color": {
                  "expr": {
                    "ThemeDataColor": {
                      "ColorId": 1,
                      "Percent": 0
                    }
                  }
                }
              }
            }
          }
        }
      ],
      "grid": [
        {
          "properties": {
            "outlineColor": {
              "solid": {
                "color": {
                  "expr": {
                    "ThemeDataColor": {
                      "ColorId": 1,
                      "Percent": 0
                    }
                  }
                }
              }
            },
            "outlineWeight": {
              "expr": {
                "Literal": {
                  "Value": "2D"
                }
              }
            },
            "gridVertical": {
              "expr": {
                "Literal": {
                  "Value": "true"
                }
              }
            },
            "gridVerticalColor": {
              "solid": {
                "color": {
                  "expr": {
                    "ThemeDataColor": {
                      "ColorId": 1,
                      "Percent": 0
                    }
                  }
                }
              }
            },
            "gridVerticalWeight": {
              "expr": {
                "Literal": {
                  "Value": "1D"
                }
              }
            },
            "gridHorizontalColor": {
              "solid": {
                "color": {
                  "expr": {
                    "ThemeDataColor": {
                      "ColorId": 1,
                      "Percent": 0
                    }
                  }
                }
              }
            },
            "gridHorizontalWeight": {
              "expr": {
                "Literal": {
                  "Value": "1D"
                }
              }
            },
            "rowPadding": {
              "expr": {
                "Literal": {
                  "Value": "4D"
                }
              }
            },
            "imageHeight": {
              "expr": {
                "Literal": {
                  "Value": "75D"
                }
              }
            },
            "outlineStyle": {
              "expr": {
                "Literal": {
                  "Value": "15D"
                }
              }
            }
          }
        }
      ],
      "columnFormatting": [
        {
          "properties": {
            "alignment": {
              "expr": {
                "Literal": {
                  "Value": "'Right'"
                }
              }
            }
          },
          "selector": {
            "metadata": "Sum(f_vendas.Unidades)"
          }
        },
        {
          "properties": {
            "alignment": {
              "expr": {
                "Literal": {
                  "Value": "'Right'"
                }
              }
            }
          },
          "selector": {
            "metadata": "d_produto.ReceitaBruta"
          }
        }
      ]
    },
    "visualContainerObjects": {
      "title": [
        {
          "properties": {
            "titleWrap": {
              "expr": {
                "Literal": {
                  "Value": "true"
                }
              }
            }
          }
        }
      ],
      "background": [
        {
          "properties": {
            "show": {
              "expr": {
                "Literal": {
                  "Value": "false"
                }
              }
            },
            "transparency": {
              "expr": {
                "Literal": {
                  "Value": "0D"
                }
              }
            }
          }
        }
      ],
      "border": [
        {
          "properties": {
            "width": {
              "expr": {
                "Literal": {
                  "Value": "1D"
                }
              }
            }
          }
        }
      ],
      "stylePreset": [
        {
          "properties": {
            "name": {
              "expr": {
                "Literal": {
                  "Value": "'None'"
                }
              }
            }
          }
        }
      ]
    },
    "drillFilterOtherVisuals": true
  }
}